ape_aws/__init__.py
ape_aws/_cli.py
ape_aws/accounts.py
ape_aws/client.py
ape_aws/config.py
ape_aws/exceptions.py
ape_aws/py.typed
ape_aws/session.py
ape_aws/utils.py
ape_aws/version.py
ape_aws/iam/__init__.py
ape_aws/iam/client.py
ape_aws/kms/__init__.py
ape_aws/kms/client.py
ape_aws-0.8.4.dist-info/licenses/LICENSE
ape_aws-0.8.4.dist-info/METADATA
ape_aws-0.8.4.dist-info/WHEEL
ape_aws-0.8.4.dist-info/entry_points.txt
ape_aws-0.8.4.dist-info/top_level.txt
ape_aws-0.8.4.dist-info/RECORD
