Metadata-Version: 2.4
Name: ape-aws
Version: 0.8.4
Summary: Ape AWS KMS: Ape plugin to make transactions through AWS KMS
Home-page: https://github.com/ApeWorX/ape-aws
Author: ApeWorX Ltd.
Author-email: admin@apeworx.io
License: Apache-2.0
Keywords: ethereum
Classifier: Development Status :: 4 - Beta
Classifier: Intended Audience :: Developers
Classifier: License :: OSI Approved :: Apache Software License
Classifier: Natural Language :: English
Classifier: Operating System :: MacOS
Classifier: Operating System :: POSIX
Classifier: Programming Language :: Python :: 3
Classifier: Programming Language :: Python :: 3.10
Classifier: Programming Language :: Python :: 3.11
Classifier: Programming Language :: Python :: 3.12
Classifier: Programming Language :: Python :: 3.13
Requires-Python: >=3.7,<4
License-File: LICENSE
Requires-Dist: importlib-metadata; python_version < "3.8"
Requires-Dist: boto3<2,>=1.34.79
Requires-Dist: eth-ape<0.9,>=0.8.2
Requires-Dist: ecdsa<1,>=0.19.0
Requires-Dist: cryptography<38,>=37.0.4
Provides-Extra: test
Requires-Dist: pytest<9.0,>=8.0; extra == "test"
Requires-Dist: pytest-xdist; extra == "test"
Requires-Dist: pytest-cov; extra == "test"
Requires-Dist: hypothesis<7.0,>=6.2.0; extra == "test"
Provides-Extra: lint
Requires-Dist: black<25,>=24.2.0; extra == "lint"
Requires-Dist: mypy<2,>=1.8.0; extra == "lint"
Requires-Dist: flake8<8,>=7.0.0; extra == "lint"
Requires-Dist: isort<6,>=5.10.1; extra == "lint"
Provides-Extra: release
Requires-Dist: setuptools>=75.6.0; extra == "release"
Requires-Dist: wheel; extra == "release"
Requires-Dist: twine; extra == "release"
Provides-Extra: dev
Requires-Dist: pytest<9.0,>=8.0; extra == "dev"
Requires-Dist: pytest-xdist; extra == "dev"
Requires-Dist: pytest-cov; extra == "dev"
Requires-Dist: hypothesis<7.0,>=6.2.0; extra == "dev"
Requires-Dist: black<25,>=24.2.0; extra == "dev"
Requires-Dist: mypy<2,>=1.8.0; extra == "dev"
Requires-Dist: flake8<8,>=7.0.0; extra == "dev"
Requires-Dist: isort<6,>=5.10.1; extra == "dev"
Requires-Dist: setuptools>=75.6.0; extra == "dev"
Requires-Dist: wheel; extra == "dev"
Requires-Dist: twine; extra == "dev"
Requires-Dist: commitizen; extra == "dev"
Requires-Dist: pre-commit; extra == "dev"
Requires-Dist: pytest-watch; extra == "dev"
Requires-Dist: IPython; extra == "dev"
Requires-Dist: ipdb; extra == "dev"
Dynamic: author
Dynamic: author-email
Dynamic: classifier
Dynamic: description
Dynamic: description-content-type
Dynamic: home-page
Dynamic: keywords
Dynamic: license
Dynamic: license-file
Dynamic: provides-extra
Dynamic: requires-dist
Dynamic: requires-python
Dynamic: summary
